Metadata-Version: 2.1
Name: ds2play
Version: 3.0
Summary: read docs in https://github.com/Kaii-Devv/ds2play
Author: Tamsis X Code
Author-email: ceeskamu@gmail.com
